kit_market_mcp/__init__.py
kit_market_mcp/server.py
kit_market_mcp/storage/__init__.py
kit_market_mcp/storage/local.py
kit_market_mcp/storage/remote.py
kit_market_mcp/tools/__init__.py
kit_market_mcp/tools/info.py
kit_market_mcp/tools/install.py
kit_market_mcp/tools/search.py
kit_market_mcp-1.0.0.dist-info/METADATA
kit_market_mcp-1.0.0.dist-info/WHEEL
kit_market_mcp-1.0.0.dist-info/entry_points.txt
kit_market_mcp-1.0.0.dist-info/RECORD
