Metadata-Version: 2.4
Name: kit-market-mcp
Version: 1.0.0
Summary: MCP Server for Kit Market - AI-powered code kit discovery and integration
Project-URL: Homepage, https://github.com/ngocnguyen88/vibe-kit-market
Project-URL: Documentation, https://github.com/ngocnguyen88/vibe-kit-market#readme
Project-URL: Repository, https://github.com/ngocnguyen88/vibe-kit-market
Project-URL: Issues, https://github.com/ngocnguyen88/vibe-kit-market/issues
Author-email: Ngoc Nguyen <ngocnguyen88@users.noreply.github.com>
License-Expression: MIT
Keywords: ai,claude,code-kit,marketplace,mcp,model-context-protocol
Classifier: Development Status :: 4 - Beta
Classifier: Intended Audience :: Developers
Classifier: License :: OSI Approved :: MIT License
Classifier: Programming Language :: Python :: 3
Classifier: Programming Language :: Python :: 3.10
Classifier: Programming Language :: Python :: 3.11
Classifier: Programming Language :: Python :: 3.12
Classifier: Topic :: Software Development :: Libraries :: Python Modules
Requires-Python: >=3.10
Requires-Dist: pyyaml>=6.0
Provides-Extra: dev
Requires-Dist: pytest-asyncio>=0.21.0; extra == 'dev'
Requires-Dist: pytest>=7.0.0; extra == 'dev'
